sbNative/__init__.py
sbNative/debugtools.py
sbNative/geometrics.py
sbNative/runtimetools.py
sbNative/sbNative.py
sbNative-0.0.17.post2.dist-info/METADATA
sbNative-0.0.17.post2.dist-info/WHEEL
sbNative-0.0.17.post2.dist-info/top_level.txt
sbNative-0.0.17.post2.dist-info/RECORD
