Metadata-Version: 2.1
Name: sbNative
Version: 0.0.17.post2
Summary: A package for all things that should be native
Home-page: https://pypi.org/project/sbNative/
Author: RICHARD_GALFI
Author-email: richardgalfi@gmail.com
Keywords: example documentation tutorial
Requires-Dist: appdirs
Requires-Dist: PyYAML
